fastgql/__init__.py
fastgql/context.py
fastgql/depends.py
fastgql/execute/__init__.py
fastgql/execute/executor.py
fastgql/execute/resolver.py
fastgql/execute/utils.py
fastgql/gql_ast/__init__.py
fastgql/gql_ast/models.py
fastgql/gql_ast/translator.py
fastgql/gql_models.py
fastgql/info.py
fastgql/logs.py
fastgql/query_builders/edgedb/config.py
fastgql/query_builders/edgedb/logic.py
fastgql/query_builders/edgedb/models.py
fastgql/query_builders/edgedb/query_builder.py
fastgql/query_builders/sql/config.py
fastgql/query_builders/sql/logic.py
fastgql/query_builders/sql/query_builder.py
fastgql/scalars.py
fastgql/schema_builder.py
fastgql/static/graphiql.html
fastgql/utils.py
fastgql-0.24.4.dist-info/METADATA
fastgql-0.24.4.dist-info/WHEEL
fastgql-0.24.4.dist-info/RECORD
