Metadata-Version: 2.1
Name: fastgql
Version: 0.24.4
Summary: The easiest, fastest python GraphQL framework.
Home-page: https://github.com/jerber/fastgql
License: MIT
Author: Jeremy Berman
Author-email: jerber@sas.upenn.edu
Requires-Python: >=3.10,<4.0
Classifier: Development Status :: 4 - Beta
Classifier: Framework :: AsyncIO
Classifier: Intended Audience :: Developers
Classifier: Intended Audience :: Science/Research
Classifier: Intended Audience :: System Administrators
Classifier: License :: OSI Approved :: MIT License
Classifier: Programming Language :: Python :: 3
Classifier: Programming Language :: Python :: 3.10
Classifier: Programming Language :: Python :: 3.11
Classifier: Programming Language :: Python :: 3.12
Classifier: Topic :: Database
Classifier: Topic :: Database :: Database Engines/Servers
Classifier: Topic :: Internet
Classifier: Topic :: Internet :: WWW/HTTP
Classifier: Topic :: Internet :: WWW/HTTP :: HTTP Servers
Classifier: Topic :: Software Development :: Libraries :: Python Modules
Classifier: Typing :: Typed
Provides-Extra: edgedb
Provides-Extra: sql
Requires-Dist: devtools
Requires-Dist: edgedb (>=1.7.0,<2.0.0) ; extra == "edgedb"
Requires-Dist: fastapi[all]
Requires-Dist: graphql-core (>=3.2.3,<4.0.0)
Requires-Dist: pydantic (>=2.7,<3.0)
Requires-Dist: sqlparse ; extra == "sql"
Requires-Dist: uvicorn[standard]
Project-URL: Documentation, https://jerber.github.io/fastgql/
Project-URL: Repository, https://github.com/jerber/fastgql
